{"address":"SP12R850GHENCPJ3RV18HTNNQRKV3734FKYK9GNK7","name":"fuck-kim-jong-un-6","block_height":1147335,"burn_block_time_iso":"2025-05-12T15:29:41.000Z","contractInterface":{"functions":[{"name":"ac605c4b","access":"private","args":[{"name":"nnnm","type":"uint128"}],"outputs":{"type":{"response":{"ok":"uint128","error":"uint128"}}}},{"name":"adfea8eb","access":"private","args":[{"name":"nnnm","type":"uint128"},{"name":"nmmm","type":"uint128"}],"outputs":{"type":{"response":{"ok":"uint128","error":"uint128"}}}},{"name":"ag29fc05","access":"private","args":[{"name":"nnnm","type":"uint128"}],"outputs":{"type":{"response":{"ok":"uint128","error":"uint128"}}}},{"name":"al02ccd7","access":"private","args":[{"name":"nnnm","type":"uint128"},{"name":"nnmm","type":"uint128"}],"outputs":{"type":{"response":{"ok":"uint128","error":"uint128"}}}},{"name":"al556a18","access":"private","args":[{"name":"nnnm","type":"uint128"}],"outputs":{"type":{"response":{"ok":"uint128","error":"uint128"}}}},{"name":"am710272","access":"private","args":[{"name":"nnnm","type":"uint128"}],"outputs":{"type":{"response":{"ok":"uint128","error":"uint128"}}}},{"name":"aq53a5aa","access":"private","args":[{"name":"nnnm","type":"uint128"},{"name":"mmmm","type":"uint128"}],"outputs":{"type":{"response":{"ok":"uint128","error":"uint128"}}}},{"name":"aq65b200","access":"private","args":[{"name":"nnnm","type":"uint128"}],"outputs":{"type":{"response":{"ok":"uint128","error":"uint128"}}}},{"name":"aq7f2e3b","access":"private","args":[{"name":"nnnm","type":"uint128"}],"outputs":{"type":{"response":{"ok":"uint128","error":"uint128"}}}},{"name":"ar6e885a","access":"private","args":[{"name":"nnnm","type":"uint128"}],"outputs":{"type":{"response":{"ok":"uint128","error":"uint128"}}}},{"name":"ax8309ce","access":"private","args":[{"name":"nnnm","type":"uint128"},{"name":"mmmm","type":"uint128"}],"outputs":{"type":{"response":{"ok":"uint128","error":"uint128"}}}},{"name":"axaa2810","access":"private","args":[{"name":"nnnm","type":"uint128"},{"name":"mmmm","type":"uint128"},{"name":"nmmm","type":"uint128"}],"outputs":{"type":{"response":{"ok":"uint128","error":"uint128"}}}},{"name":"bc0d37e8","access":"private","args":[{"name":"nnnm","type":"uint128"},{"name":"mmmm","type":"uint128"}],"outputs":{"type":{"response":{"ok":"uint128","error":"uint128"}}}},{"name":"bh8df448","access":"private","args":[{"name":"nnnm","type":"uint128"},{"name":"nmmm","type":"uint128"}],"outputs":{"type":{"response":{"ok":"uint128","error":"uint128"}}}},{"name":"bk8a6949","access":"private","args":[{"name":"nnnm","type":"uint128"}],"outputs":{"type":{"response":{"ok":"uint128","error":"uint128"}}}},{"name":"bkd0d1e8","access":"private","args":[{"name":"nnnm","type":"uint128"}],"outputs":{"type":{"response":{"ok":"uint128","error":"uint128"}}}},{"name":"bl7f82ac","access":"private","args":[{"name":"nnnm","type":"uint128"},{"name":"nmmm","type":"uint128"}],"outputs":{"type":{"response":{"ok":"uint128","error":"uint128"}}}},{"name":"br9aa86d","access":"private","args":[{"name":"nnnm","type":"uint128"},{"name":"nmmm","type":"uint128"}],"outputs":{"type":{"response":{"ok":"uint128","error":"uint128"}}}},{"name":"bs5656b3","access":"private","args":[{"name":"nnnm","type":"uint128"}],"outputs":{"type":{"response":{"ok":"uint128","error":"uint128"}}}},{"name":"bu302353","access":"private","args":[{"name":"nnnm","type":"uint128"}],"outputs":{"type":{"response":{"ok":"uint128","error":"uint128"}}}},{"name":"bu514a39","access":"private","args":[{"name":"nnnm","type":"uint128"}],"outputs":{"type":{"response":{"ok":"uint128","error":"uint128"}}}},{"name":"cc38fe90","access":"private","args":[{"name":"nnnm","type":"uint128"},{"name":"nmmm","type":"uint128"}],"outputs":{"type":{"response":{"ok":"uint128","error":"uint128"}}}},{"name":"cc4d8ae3","access":"private","args":[{"name":"nnnm","type":"uint128"},{"name":"nmmm","type":"uint128"}],"outputs":{"type":{"response":{"ok":"uint128","error":"uint128"}}}},{"name":"ci364195","access":"private","args":[{"name":"nnnm","type":"uint128"}],"outputs":{"type":{"response":{"ok":"uint128","error":"uint128"}}}},{"name":"co7be266","access":"private","args":[{"name":"nnnm","type":"uint128"},{"name":"nmmm","type":"uint128"},{"name":"nnmm","type":"uint128"}],"outputs":{"type":{"response":{"ok":"uint128","error":"uint128"}}}},{"name":"ct5330e1","access":"private","args":[{"name":"nnnm","type":"uint128"}],"outputs":{"type":{"response":{"ok":"uint128","error":"uint128"}}}},{"name":"cw4abc7b","access":"private","args":[{"name":"nnnm","type":"uint128"}],"outputs":{"type":{"response":{"ok":"uint128","error":"uint128"}}}},{"name":"db719b0c","access":"private","args":[{"name":"nnnm","type":"uint128"},{"name":"mmmm","type":"uint128"}],"outputs":{"type":{"response":{"ok":"uint128","error":"uint128"}}}},{"name":"de3d15b9","access":"private","args":[{"name":"nnnm","type":"uint128"}],"outputs":{"type":{"response":{"ok":"uint128","error":"uint128"}}}},{"name":"dee894dc","access":"private","args":[{"name":"nnnm","type":"uint128"}],"outputs":{"type":{"response":{"ok":"uint128","error":"uint128"}}}},{"name":"dh6bfa13","access":"private","args":[{"name":"nnnm","type":"uint128"}],"outputs":{"type":{"response":{"ok":"uint128","error":"uint128"}}}},{"name":"dk303bff","access":"private","args":[{"name":"nnnm","type":"uint128"},{"name":"mmmm","type":"uint128"}],"outputs":{"type":{"response":{"ok":"uint128","error":"uint128"}}}},{"name":"dk8e8def","access":"private","args":[{"name":"nnnm","type":"uint128"},{"name":"nmmm","type":"uint128"},{"name":"nnmm","type":"uint128"}],"outputs":{"type":{"response":{"ok":"uint128","error":"uint128"}}}},{"name":"dn20f8c5","access":"private","args":[{"name":"nnnm","type":"uint128"}],"outputs":{"type":{"response":{"ok":"uint128","error":"uint128"}}}},{"name":"do0e8b84","access":"private","args":[{"name":"nnnm","type":"uint128"},{"name":"mmmm","type":"uint128"},{"name":"nmmm","type":"uint128"}],"outputs":{"type":{"response":{"ok":"uint128","error":"uint128"}}}},{"name":"dpa8b8fa","access":"private","args":[{"name":"nnnm","type":"uint128"}],"outputs":{"type":{"response":{"ok":"uint128","error":"uint128"}}}},{"name":"ed0788c6","access":"private","args":[{"name":"nnnm","type":"uint128"}],"outputs":{"type":{"response":{"ok":"uint128","error":"uint128"}}}},{"name":"ehe1e97f","access":"private","args":[{"name":"nnnm","type":"uint128"}],"outputs":{"type":{"response":{"ok":"uint128","error":"uint128"}}}},{"name":"eoa72dd5","access":"private","args":[{"name":"nnnm","type":"uint128"}],"outputs":{"type":{"response":{"ok":"uint128","error":"uint128"}}}},{"name":"eqf63320","access":"private","args":[{"name":"nnnm","type":"uint128"}],"outputs":{"type":{"response":{"ok":"uint128","error":"uint128"}}}},{"name":"es7925d2","access":"private","args":[{"name":"nnnm","type":"uint128"},{"name":"nmmm","type":"uint128"}],"outputs":{"type":{"response":{"ok":"uint128","error":"uint128"}}}},{"name":"et8c878f","access":"private","args":[{"name":"nnnm","type":"uint128"},{"name":"mmmm","type":"uint128"}],"outputs":{"type":{"response":{"ok":"uint128","error":"uint128"}}}},{"name":"etdbe9e4","access":"private","args":[{"name":"nnnm","type":"uint128"}],"outputs":{"type":{"response":{"ok":"uint128","error":"uint128"}}}},{"name":"eu3e7a25","access":"private","args":[{"name":"nnnm","type":"uint128"}],"outputs":{"type":{"response":{"ok":"uint128","error":"uint128"}}}},{"name":"euc2e6c9","access":"private","args":[{"name":"nnnm","type":"uint128"},{"name":"mmmm","type":"uint128"}],"outputs":{"type":{"response":{"ok":"uint128","error":"uint128"}}}},{"name":"ev3a58f4","access":"private","args":[{"name":"nnnm","type":"uint128"},{"name":"mmmm","type":"uint128"}],"outputs":{"type":{"response":{"ok":"uint128","error":"uint128"}}}},{"name":"eve800d0","access":"private","args":[{"name":"nnnm","type":"uint128"}],"outputs":{"type":{"response":{"ok":"uint128","error":"uint128"}}}},{"name":"fib53bfb","access":"private","args":[{"name":"nnnm","type":"uint128"},{"name":"nmmm","type":"uint128"}],"outputs":{"type":{"response":{"ok":"uint128","error":"uint128"}}}},{"name":"fl24455f","access":"private","args":[{"name":"nnnm","type":"uint128"}],"outputs":{"type":{"response":{"ok":"uint128","error":"uint128"}}}},{"name":"fu04351e","access":"private","args":[{"name":"nnnm","type":"uint128"}],"outputs":{"type":{"response":{"ok":"uint128","error":"uint128"}}}},{"name":"fuf23a33","access":"private","args":[{"name":"nnnm","type":"uint128"},{"name":"mmmm","type":"uint128"}],"outputs":{"type":{"response":{"ok":"uint128","error":"uint128"}}}},{"name":"fz3cd322","access":"private","args":[{"name":"nnnm","type":"uint128"},{"name":"mmmm","type":"uint128"}],"outputs":{"type":{"response":{"ok":"uint128","error":"uint128"}}}},{"name":"gc13b250","access":"private","args":[{"name":"nnnm","type":"uint128"}],"outputs":{"type":{"response":{"ok":"uint128","error":"uint128"}}}},{"name":"gfd190a6","access":"private","args":[{"name":"nnnm","type":"uint128"}],"outputs":{"type":{"response":{"ok":"uint128","error":"uint128"}}}},{"name":"gm8e1415","access":"private","args":[{"name":"nnnm","type":"uint128"},{"name":"nmmm","type":"uint128"}],"outputs":{"type":{"response":{"ok":"uint128","error":"uint128"}}}},{"name":"gt93fcff","access":"private","args":[{"name":"nnnm","type":"uint128"},{"name":"nmmm","type":"uint128"},{"name":"nnmm","type":"uint128"}],"outputs":{"type":{"response":{"ok":"uint128","error":"uint128"}}}},{"name":"gz21db85","access":"private","args":[{"name":"nnnm","type":"uint128"},{"name":"mmmm","type":"uint128"}],"outputs":{"type":{"response":{"ok":"uint128","error":"uint128"}}}},{"name":"hb7aed7a","access":"private","args":[{"name":"nnnm","type":"uint128"}],"outputs":{"type":{"response":{"ok":"uint128","error":"uint128"}}}},{"name":"hi9d1eb4","access":"private","args":[{"name":"nnnm","type":"uint128"}],"outputs":{"type":{"response":{"ok":"uint128","error":"uint128"}}}},{"name":"hnfdf5cd","access":"private","args":[{"name":"nnnm","type":"uint128"}],"outputs":{"type":{"response":{"ok":"uint128","error":"uint128"}}}},{"name":"hp4b86e0","access":"private","args":[{"name":"nnnm","type":"uint128"},{"name":"nmmm","type":"uint128"}],"outputs":{"type":{"response":{"ok":"uint128","error":"uint128"}}}},{"name":"hr72612b","access":"private","args":[{"name":"nnnm","type":"uint128"},{"name":"nnmm","type":"uint128"}],"outputs":{"type":{"response":{"ok":"uint128","error":"uint128"}}}},{"name":"ht85ecc6","access":"private","args":[{"name":"nnnm","type":"uint128"},{"name":"mmmm","type":"uint128"},{"name":"nmmm","type":"uint128"},{"name":"nnmm","type":"uint128"}],"outputs":{"type":{"response":{"ok":"uint128","error":"uint128"}}}},{"name":"hxaadb0a","access":"private","args":[{"name":"nnnm","type":"uint128"},{"name":"nnmm","type":"uint128"}],"outputs":{"type":{"response":{"ok":"uint128","error":"uint128"}}}},{"name":"ia48f1b1","access":"private","args":[{"name":"nnnm","type":"uint128"},{"name":"mmmm","type":"uint128"},{"name":"nmmm","type":"uint128"}],"outputs":{"type":{"response":{"ok":"uint128","error":"uint128"}}}},{"name":"ihd07bd6","access":"private","args":[{"name":"nnnm","type":"uint128"}],"outputs":{"type":{"response":{"ok":"uint128","error":"uint128"}}}},{"name":"io1fb08e","access":"private","args":[{"name":"nnnm","type":"uint128"},{"name":"nmmm","type":"uint128"}],"outputs":{"type":{"response":{"ok":"uint128","error":"uint128"}}}},{"name":"ipbfd5d9","access":"private","args":[{"name":"nnnm","type":"uint128"}],"outputs":{"type":{"response":{"ok":"uint128","error":"uint128"}}}},{"name":"ipdc4280","access":"private","args":[{"name":"nnnm","type":"uint128"}],"outputs":{"type":{"response":{"ok":"uint128","error":"uint128"}}}},{"name":"ite00c1d","access":"private","args":[{"name":"nnnm","type":"uint128"}],"outputs":{"type":{"response":{"ok":"uint128","error":"uint128"}}}},{"name":"ivbdacef","access":"private","args":[{"name":"nnnm","type":"uint128"},{"name":"mmmm","type":"uint128"}],"outputs":{"type":{"response":{"ok":"uint128","error":"uint128"}}}},{"name":"ixbe9baf","access":"private","args":[{"name":"nnnm","type":"uint128"},{"name":"mmmm","type":"uint128"}],"outputs":{"type":{"response":{"ok":"uint128","error":"uint128"}}}},{"name":"ji46874c","access":"private","args":[{"name":"nnnm","type":"uint128"},{"name":"nmmm","type":"uint128"}],"outputs":{"type":{"response":{"ok":"uint128","error":"uint128"}}}},{"name":"jk21e288","access":"private","args":[{"name":"nnnm","type":"uint128"},{"name":"mmmm","type":"uint128"}],"outputs":{"type":{"response":{"ok":"uint128","error":"uint128"}}}},{"name":"jo5c5202","access":"private","args":[{"name":"nnnm","type":"uint128"},{"name":"mmmm","type":"uint128"}],"outputs":{"type":{"response":{"ok":"uint128","error":"uint128"}}}},{"name":"jpa0194f","access":"private","args":[{"name":"nnnm","type":"uint128"}],"outputs":{"type":{"response":{"ok":"uint128","error":"uint128"}}}},{"name":"jvfd94d3","access":"private","args":[{"name":"nnnm","type":"uint128"}],"outputs":{"type":{"response":{"ok":"uint128","error":"uint128"}}}},{"name":"jx641d8d","access":"private","args":[{"name":"nnnm","type":"uint128"}],"outputs":{"type":{"response":{"ok":"uint128","error":"uint128"}}}},{"name":"jxe0ab56","access":"private","args":[{"name":"nnnm","type":"uint128"}],"outputs":{"type":{"response":{"ok":"uint128","error":"uint128"}}}},{"name":"km9ddef4","access":"private","args":[{"name":"nnnm","type":"uint128"}],"outputs":{"type":{"response":{"ok":"uint128","error":"uint128"}}}},{"name":"koe04cd4","access":"private","args":[{"name":"nnnm","type":"uint128"},{"name":"nnmm","type":"uint128"}],"outputs":{"type":{"response":{"ok":"uint128","error":"uint128"}}}},{"name":"kqf49927","access":"private","args":[{"name":"nnnm","type":"uint128"}],"outputs":{"type":{"response":{"ok":"uint128","error":"uint128"}}}},{"name":"ksf50089","access":"private","args":[{"name":"nnnm","type":"uint128"},{"name":"mmmm","type":"uint128"}],"outputs":{"type":{"response":{"ok":"uint128","error":"uint128"}}}},{"name":"lda7965e","access":"private","args":[{"name":"nnnm","type":"uint128"}],"outputs":{"type":{"response":{"ok":"uint128","error":"uint128"}}}},{"name":"lhab4509","access":"private","args":[{"name":"nnnm","type":"uint128"},{"name":"mmmm","type":"uint128"}],"outputs":{"type":{"response":{"ok":"uint128","error":"uint128"}}}},{"name":"ln2cbe6d","access":"private","args":[{"name":"nnnm","type":"uint128"},{"name":"mmmm","type":"uint128"}],"outputs":{"type":{"response":{"ok":"uint128","error":"uint128"}}}},{"name":"lr04d77c","access":"private","args":[{"name":"nnnm","type":"uint128"},{"name":"nnmm","type":"uint128"}],"outputs":{"type":{"response":{"ok":"uint128","error":"uint128"}}}},{"name":"ls4f981f","access":"private","args":[{"name":"nnnm","type":"uint128"}],"outputs":{"type":{"response":{"ok":"uint128","error":"uint128"}}}},{"name":"lsc98953","access":"private","args":[{"name":"nnnm","type":"uint128"},{"name":"mmmm","type":"uint128"}],"outputs":{"type":{"response":{"ok":"uint128","error":"uint128"}}}},{"name":"mb02b108","access":"private","args":[{"name":"nnnm","type":"uint128"}],"outputs":{"type":{"response":{"ok":"uint128","error":"uint128"}}}},{"name":"mcfb7287","access":"private","args":[{"name":"nnnm","type":"uint128"}],"outputs":{"type":{"response":{"ok":"uint128","error":"uint128"}}}},{"name":"mr7db94b","access":"private","args":[{"name":"nnnm","type":"uint128"},{"name":"mmmm","type":"uint128"},{"name":"nmmm","type":"uint128"}],"outputs":{"type":{"response":{"ok":"uint128","error":"uint128"}}}},{"name":"mrd822ce","access":"private","args":[{"name":"nnnm","type":"uint128"},{"name":"nmmm","type":"uint128"}],"outputs":{"type":{"response":{"ok":"uint128","error":"uint128"}}}},{"name":"ms42d3d7","access":"private","args":[{"name":"nnnm","type":"uint128"}],"outputs":{"type":{"response":{"ok":"uint128","error":"uint128"}}}},{"name":"mw1ca299","access":"private","args":[{"name":"nnnm","type":"uint128"},{"name":"mmmm","type":"uint128"},{"name":"nmmm","type":"uint128"}],"outputs":{"type":{"response":{"ok":"uint128","error":"uint128"}}}},{"name":"my2bfe8a","access":"private","args":[{"name":"nnnm","type":"uint128"},{"name":"mmmm","type":"uint128"}],"outputs":{"type":{"response":{"ok":"uint128","error":"uint128"}}}},{"name":"nb3f258f","access":"private","args":[{"name":"nnnm","type":"uint128"},{"name":"mmmm","type":"uint128"}],"outputs":{"type":{"response":{"ok":"uint128","error":"uint128"}}}},{"name":"nc3abd57","access":"private","args":[{"name":"nnnm","type":"uint128"},{"name":"mmmm","type":"uint128"},{"name":"nmmm","type":"uint128"}],"outputs":{"type":{"response":{"ok":"uint128","error":"uint128"}}}},{"name":"nfb1c8ee","access":"private","args":[{"name":"nnnm","type":"uint128"}],"outputs":{"type":{"response":{"ok":"uint128","error":"uint128"}}}},{"name":"nkdd204b","access":"private","args":[{"name":"nnnm","type":"uint128"}],"outputs":{"type":{"response":{"ok":"uint128","error":"uint128"}}}},{"name":"nob2e14b","access":"private","args":[{"name":"nnnm","type":"uint128"},{"name":"nnmm","type":"uint128"}],"outputs":{"type":{"response":{"ok":"uint128","error":"uint128"}}}},{"name":"nu32b0cf","access":"private","args":[{"name":"nnnm","type":"uint128"},{"name":"mmmm","type":"uint128"},{"name":"nmmm","type":"uint128"}],"outputs":{"type":{"response":{"ok":"uint128","error":"uint128"}}}},{"name":"ok1b26d3","access":"private","args":[{"name":"nnnm","type":"uint128"},{"name":"nmmm","type":"uint128"},{"name":"nnmm","type":"uint128"}],"outputs":{"type":{"response":{"ok":"uint128","error":"uint128"}}}},{"name":"okb09520","access":"private","args":[{"name":"nnnm","type":"uint128"},{"name":"mmmm","type":"uint128"}],"outputs":{"type":{"response":{"ok":"uint128","error":"uint128"}}}},{"name":"olcdd24e","access":"private","args":[{"name":"nnnm","type":"uint128"},{"name":"nmmm","type":"uint128"}],"outputs":{"type":{"response":{"ok":"uint128","error":"uint128"}}}},{"name":"op3b4392","access":"private","args":[{"name":"nnnm","type":"uint128"},{"name":"mmmm","type":"uint128"}],"outputs":{"type":{"response":{"ok":"uint128","error":"uint128"}}}},{"name":"op4d71ad","access":"private","args":[{"name":"nnnm","type":"uint128"},{"name":"mmmm","type":"uint128"},{"name":"nmmm","type":"uint128"}],"outputs":{"type":{"response":{"ok":"uint128","error":"uint128"}}}},{"name":"or8b46ed","access":"private","args":[{"name":"nnnm","type":"uint128"},{"name":"mmmm","type":"uint128"}],"outputs":{"type":{"response":{"ok":"uint128","error":"uint128"}}}},{"name":"ow78a294","access":"private","args":[{"name":"nnnm","type":"uint128"},{"name":"nmmm","type":"uint128"}],"outputs":{"type":{"response":{"ok":"uint128","error":"uint128"}}}},{"name":"pa3c56f7","access":"private","args":[{"name":"nnnm","type":"uint128"},{"name":"mmmm","type":"uint128"}],"outputs":{"type":{"response":{"ok":"uint128","error":"uint128"}}}},{"name":"pa844acb","access":"private","args":[{"name":"nnnm","type":"uint128"},{"name":"mmmm","type":"uint128"}],"outputs":{"type":{"response":{"ok":"uint128","error":"uint128"}}}},{"name":"pd809ab2","access":"private","args":[{"name":"nnnm","type":"uint128"}],"outputs":{"type":{"response":{"ok":"uint128","error":"uint128"}}}},{"name":"pe4b15e8","access":"private","args":[{"name":"nnnm","type":"uint128"}],"outputs":{"type":{"response":{"ok":"uint128","error":"uint128"}}}},{"name":"plf41b0d","access":"private","args":[{"name":"nnnm","type":"uint128"},{"name":"mmmm","type":"uint128"},{"name":"nmmm","type":"uint128"}],"outputs":{"type":{"response":{"ok":"uint128","error":"uint128"}}}},{"name":"pm10dbbe","access":"private","args":[{"name":"nnnm","type":"uint128"},{"name":"nmmm","type":"uint128"}],"outputs":{"type":{"response":{"ok":"uint128","error":"uint128"}}}},{"name":"pm9aafb7","access":"private","args":[{"name":"nnnm","type":"uint128"},{"name":"mmmm","type":"uint128"}],"outputs":{"type":{"response":{"ok":"uint128","error":"uint128"}}}},{"name":"pofbbbd4","access":"private","args":[{"name":"nnnm","type":"uint128"}],"outputs":{"type":{"response":{"ok":"uint128","error":"uint128"}}}},{"name":"ppeaf252","access":"private","args":[{"name":"nnnm","type":"uint128"},{"name":"mmmm","type":"uint128"}],"outputs":{"type":{"response":{"ok":"uint128","error":"uint128"}}}},{"name":"pq26138e","access":"private","args":[{"name":"nnnm","type":"uint128"},{"name":"nnmm","type":"uint128"}],"outputs":{"type":{"response":{"ok":"uint128","error":"uint128"}}}},{"name":"qf8726a8","access":"private","args":[{"name":"nnnm","type":"uint128"}],"outputs":{"type":{"response":{"ok":"uint128","error":"uint128"}}}},{"name":"qo03a003","access":"private","args":[{"name":"nnnm","type":"uint128"},{"name":"mmmm","type":"uint128"}],"outputs":{"type":{"response":{"ok":"uint128","error":"uint128"}}}},{"name":"qr427a28","access":"private","args":[{"name":"nnnm","type":"uint128"},{"name":"nmmm","type":"uint128"},{"name":"nnmm","type":"uint128"}],"outputs":{"type":{"response":{"ok":"uint128","error":"uint128"}}}},{"name":"qw823ff9","access":"private","args":[{"name":"nnnm","type":"uint128"}],"outputs":{"type":{"response":{"ok":"uint128","error":"uint128"}}}},{"name":"rifad4a4","access":"private","args":[{"name":"nnnm","type":"uint128"},{"name":"mmmm","type":"uint128"},{"name":"nmmm","type":"uint128"}],"outputs":{"type":{"response":{"ok":"uint128","error":"uint128"}}}},{"name":"rk84ac6d","access":"private","args":[{"name":"nnnm","type":"uint128"},{"name":"mmmm","type":"uint128"}],"outputs":{"type":{"response":{"ok":"uint128","error":"uint128"}}}},{"name":"ro5d74d5","access":"private","args":[{"name":"nnnm","type":"uint128"},{"name":"mmmm","type":"uint128"}],"outputs":{"type":{"response":{"ok":"uint128","error":"uint128"}}}},{"name":"ro759d00","access":"private","args":[{"name":"nnnm","type":"uint128"},{"name":"nnmm","type":"uint128"}],"outputs":{"type":{"response":{"ok":"uint128","error":"uint128"}}}},{"name":"rse9b4e6","access":"private","args":[{"name":"nnnm","type":"uint128"},{"name":"mmmm","type":"uint128"},{"name":"nmmm","type":"uint128"},{"name":"nnmm","type":"uint128"}],"outputs":{"type":{"response":{"ok":"uint128","error":"uint128"}}}},{"name":"ru194990","access":"private","args":[{"name":"nnnm","type":"uint128"},{"name":"nmmm","type":"uint128"}],"outputs":{"type":{"response":{"ok":"uint128","error":"uint128"}}}},{"name":"rx9a3133","access":"private","args":[{"name":"nnnm","type":"uint128"},{"name":"nmmm","type":"uint128"},{"name":"nnmm","type":"uint128"}],"outputs":{"type":{"response":{"ok":"uint128","error":"uint128"}}}},{"name":"sa971bb9","access":"private","args":[{"name":"nnnm","type":"uint128"}],"outputs":{"type":{"response":{"ok":"uint128","error":"uint128"}}}},{"name":"saca1335","access":"private","args":[{"name":"nnnm","type":"uint128"},{"name":"nmmm","type":"uint128"}],"outputs":{"type":{"response":{"ok":"uint128","error":"uint128"}}}},{"name":"sae63f13","access":"private","args":[{"name":"nnnm","type":"uint128"},{"name":"mmmm","type":"uint128"}],"outputs":{"type":{"response":{"ok":"uint128","error":"uint128"}}}},{"name":"sj30deda","access":"private","args":[{"name":"nnnm","type":"uint128"}],"outputs":{"type":{"response":{"ok":"uint128","error":"uint128"}}}},{"name":"slb4cd2d","access":"private","args":[{"name":"nnnm","type":"uint128"},{"name":"nmmm","type":"uint128"}],"outputs":{"type":{"response":{"ok":"uint128","error":"uint128"}}}},{"name":"sn0be9e4","access":"private","args":[{"name":"nnnm","type":"uint128"}],"outputs":{"type":{"response":{"ok":"uint128","error":"uint128"}}}},{"name":"sn8c2507","access":"private","args":[{"name":"nnnm","type":"uint128"}],"outputs":{"type":{"response":{"ok":"uint128","error":"uint128"}}}},{"name":"sr846a18","access":"private","args":[{"name":"nnnm","type":"uint128"},{"name":"nmmm","type":"uint128"}],"outputs":{"type":{"response":{"ok":"uint128","error":"uint128"}}}},{"name":"ss230d6a","access":"private","args":[{"name":"nnnm","type":"uint128"}],"outputs":{"type":{"response":{"ok":"uint128","error":"uint128"}}}},{"name":"sv4b0dd9","access":"private","args":[{"name":"nnnm","type":"uint128"}],"outputs":{"type":{"response":{"ok":"uint128","error":"uint128"}}}},{"name":"syd8e75a","access":"private","args":[{"name":"nnnm","type":"uint128"},{"name":"mmmm","type":"uint128"}],"outputs":{"type":{"response":{"ok":"uint128","error":"uint128"}}}},{"name":"ta549cac","access":"private","args":[{"name":"nnnm","type":"uint128"},{"name":"mmmm","type":"uint128"}],"outputs":{"type":{"response":{"ok":"uint128","error":"uint128"}}}},{"name":"tb12d6fd","access":"private","args":[{"name":"nnnm","type":"uint128"},{"name":"nnmm","type":"uint128"}],"outputs":{"type":{"response":{"ok":"uint128","error":"uint128"}}}},{"name":"tg49bc5f","access":"private","args":[{"name":"nnnm","type":"uint128"},{"name":"mmmm","type":"uint128"},{"name":"nmmm","type":"uint128"}],"outputs":{"type":{"response":{"ok":"uint128","error":"uint128"}}}},{"name":"tgae98ab","access":"private","args":[{"name":"nnnm","type":"uint128"},{"name":"mmmm","type":"uint128"}],"outputs":{"type":{"response":{"ok":"uint128","error":"uint128"}}}},{"name":"tq9cedcf","access":"private","args":[{"name":"nnnm","type":"uint128"},{"name":"mmmm","type":"uint128"}],"outputs":{"type":{"response":{"ok":"uint128","error":"uint128"}}}},{"name":"ue1f8ce3","access":"private","args":[{"name":"nnnm","type":"uint128"}],"outputs":{"type":{"response":{"ok":"uint128","error":"uint128"}}}},{"name":"uf137b81","access":"private","args":[{"name":"nnnm","type":"uint128"},{"name":"nnmm","type":"uint128"}],"outputs":{"type":{"response":{"ok":"uint128","error":"uint128"}}}},{"name":"umf39018","access":"private","args":[{"name":"nnnm","type":"uint128"},{"name":"mmmm","type":"uint128"}],"outputs":{"type":{"response":{"ok":"uint128","error":"uint128"}}}},{"name":"uo086cc6","access":"private","args":[{"name":"nnnm","type":"uint128"}],"outputs":{"type":{"response":{"ok":"uint128","error":"uint128"}}}},{"name":"up606917","access":"private","args":[{"name":"nnnm","type":"uint128"}],"outputs":{"type":{"response":{"ok":"uint128","error":"uint128"}}}},{"name":"up768615","access":"private","args":[{"name":"nnnm","type":"uint128"},{"name":"nnmm","type":"uint128"}],"outputs":{"type":{"response":{"ok":"uint128","error":"uint128"}}}},{"name":"uu260d5a","access":"private","args":[{"name":"nnnm","type":"uint128"},{"name":"mmmm","type":"uint128"}],"outputs":{"type":{"response":{"ok":"uint128","error":"uint128"}}}},{"name":"vbbaa851","access":"private","args":[{"name":"nnnm","type":"uint128"}],"outputs":{"type":{"response":{"ok":"uint128","error":"uint128"}}}},{"name":"vd5a5f9c","access":"private","args":[{"name":"nnnm","type":"uint128"}],"outputs":{"type":{"response":{"ok":"uint128","error":"uint128"}}}},{"name":"vie91faf","access":"private","args":[{"name":"nnnm","type":"uint128"}],"outputs":{"type":{"response":{"ok":"uint128","error":"uint128"}}}},{"name":"vlaaab0f","access":"private","args":[{"name":"nnnm","type":"uint128"},{"name":"mmmm","type":"uint128"},{"name":"nmmm","type":"uint128"}],"outputs":{"type":{"response":{"ok":"uint128","error":"uint128"}}}},{"name":"vr6b9453","access":"private","args":[{"name":"nnnm","type":"uint128"}],"outputs":{"type":{"response":{"ok":"uint128","error":"uint128"}}}},{"name":"vya745e1","access":"private","args":[{"name":"nnnm","type":"uint128"},{"name":"mmmm","type":"uint128"}],"outputs":{"type":{"response":{"ok":"uint128","error":"uint128"}}}},{"name":"wf17bfd1","access":"private","args":[{"name":"nnnm","type":"uint128"},{"name":"nmmm","type":"uint128"},{"name":"nnmm","type":"uint128"}],"outputs":{"type":{"response":{"ok":"uint128","error":"uint128"}}}},{"name":"wnf49f43","access":"private","args":[{"name":"nnnm","type":"uint128"},{"name":"nmmm","type":"uint128"}],"outputs":{"type":{"response":{"ok":"uint128","error":"uint128"}}}},{"name":"wq452199","access":"private","args":[{"name":"nnnm","type":"uint128"}],"outputs":{"type":{"response":{"ok":"uint128","error":"uint128"}}}},{"name":"wqe2bf30","access":"private","args":[{"name":"nnnm","type":"uint128"},{"name":"mmmm","type":"uint128"}],"outputs":{"type":{"response":{"ok":"uint128","error":"uint128"}}}},{"name":"xi68721d","access":"private","args":[{"name":"nnnm","type":"uint128"},{"name":"nmmm","type":"uint128"}],"outputs":{"type":{"response":{"ok":"uint128","error":"uint128"}}}},{"name":"xj4531e1","access":"private","args":[{"name":"nnnm","type":"uint128"},{"name":"mmmm","type":"uint128"}],"outputs":{"type":{"response":{"ok":"uint128","error":"uint128"}}}},{"name":"xj633ae3","access":"private","args":[{"name":"nnnm","type":"uint128"}],"outputs":{"type":{"response":{"ok":"uint128","error":"uint128"}}}},{"name":"xx772b2e","access":"private","args":[{"name":"nnnm","type":"uint128"}],"outputs":{"type":{"response":{"ok":"uint128","error":"uint128"}}}},{"name":"xxaad6d0","access":"private","args":[{"name":"nnnm","type":"uint128"}],"outputs":{"type":{"response":{"ok":"uint128","error":"uint128"}}}},{"name":"yu82cd83","access":"private","args":[{"name":"nnnm","type":"uint128"}],"outputs":{"type":{"response":{"ok":"uint128","error":"uint128"}}}},{"name":"yw599d66","access":"private","args":[{"name":"nnnm","type":"uint128"}],"outputs":{"type":{"response":{"ok":"uint128","error":"uint128"}}}},{"name":"yy6522ce","access":"private","args":[{"name":"nnnm","type":"uint128"}],"outputs":{"type":{"response":{"ok":"uint128","error":"uint128"}}}},{"name":"za70825d","access":"private","args":[{"name":"nnnm","type":"uint128"}],"outputs":{"type":{"response":{"ok":"uint128","error":"uint128"}}}},{"name":"zd0cda8b","access":"private","args":[{"name":"nnnm","type":"uint128"},{"name":"nmmm","type":"uint128"}],"outputs":{"type":{"response":{"ok":"uint128","error":"uint128"}}}},{"name":"zi4d3609","access":"private","args":[{"name":"nnnm","type":"uint128"},{"name":"nmmm","type":"uint128"},{"name":"nnmm","type":"uint128"}],"outputs":{"type":{"response":{"ok":"uint128","error":"uint128"}}}},{"name":"zkccf09c","access":"private","args":[{"name":"nnnm","type":"uint128"}],"outputs":{"type":{"response":{"ok":"uint128","error":"uint128"}}}},{"name":"zr4c5fee","access":"private","args":[{"name":"nnnm","type":"uint128"},{"name":"mmmm","type":"uint128"}],"outputs":{"type":{"response":{"ok":"uint128","error":"uint128"}}}},{"name":"zta76f5b","access":"private","args":[{"name":"nnnm","type":"uint128"}],"outputs":{"type":{"response":{"ok":"uint128","error":"uint128"}}}},{"name":"zu879165","access":"private","args":[{"name":"nnnm","type":"uint128"},{"name":"mmmm","type":"uint128"}],"outputs":{"type":{"response":{"ok":"uint128","error":"uint128"}}}},{"name":"zv937858","access":"private","args":[{"name":"nnnm","type":"uint128"}],"outputs":{"type":{"response":{"ok":"uint128","error":"uint128"}}}},{"name":"zw960718","access":"private","args":[{"name":"nnnm","type":"uint128"},{"name":"mmmm","type":"uint128"}],"outputs":{"type":{"response":{"ok":"uint128","error":"uint128"}}}},{"name":"zz7fa6b1","access":"private","args":[{"name":"nnnm","type":"uint128"},{"name":"nnmm","type":"uint128"}],"outputs":{"type":{"response":{"ok":"uint128","error":"uint128"}}}},{"name":"zzafd61b","access":"private","args":[{"name":"nnnm","type":"uint128"}],"outputs":{"type":{"response":{"ok":"uint128","error":"uint128"}}}},{"name":"dispatch","access":"public","args":[{"name":"i","type":{"buffer":{"length":3}}},{"name":"nnnm","type":"uint128"},{"name":"nnnn","type":"uint128"},{"name":"mmmm","type":"uint128"},{"name":"nmmm","type":"uint128"},{"name":"nnmm","type":"uint128"}],"outputs":{"type":{"response":{"ok":"uint128","error":"uint128"}}}}],"variables":[{"name":"this","type":"principal","access":"constant"}],"maps":[],"fungible_tokens":[],"non_fungible_tokens":[]},"sip9":false,"sip10":false,"commission":false,"operable":false}