{"address":"SP1W7FX8P1G721KQMQ2MA2G1G4WCVVPD9JZMGXK8R","name":"farming-send","block_height":156120,"burn_block_time_iso":"2024-07-02T14:13:19.000Z","contractInterface":{"functions":[{"name":"send","access":"public","args":[{"name":"token","type":"trait_reference"},{"name":"amt","type":"uint128"},{"name":"to","type":"trait_reference"}],"outputs":{"type":{"response":{"ok":"bool","error":"uint128"}}}}],"variables":[{"name":"err-send-postconditions","type":{"response":{"ok":"none","error":"uint128"}},"access":"constant"},{"name":"err-send-preconditions","type":{"response":{"ok":"none","error":"uint128"}},"access":"constant"}],"maps":[],"fungible_tokens":[],"non_fungible_tokens":[]},"sip9":false,"sip10":false,"commission":false,"operable":false}