{"address":"SP2SVNTERTSMR695HP3FC4DTVK5D6FPA6X0QRRCAT","name":"fuck-kim-jong-un-2","block_height":1138334,"burn_block_time_iso":"2025-05-11T15:32:16.000Z","contractInterface":{"functions":[{"name":"aj93531e","access":"private","args":[{"name":"nnnm","type":"uint128"},{"name":"nnmm","type":"uint128"}],"outputs":{"type":{"response":{"ok":"uint128","error":"uint128"}}}},{"name":"al739563","access":"private","args":[{"name":"nnnm","type":"uint128"}],"outputs":{"type":{"response":{"ok":"uint128","error":"uint128"}}}},{"name":"aq834cd3","access":"private","args":[{"name":"nnnm","type":"uint128"},{"name":"nnmm","type":"uint128"}],"outputs":{"type":{"response":{"ok":"uint128","error":"uint128"}}}},{"name":"ba4c6de0","access":"private","args":[{"name":"nnnm","type":"uint128"}],"outputs":{"type":{"response":{"ok":"uint128","error":"uint128"}}}},{"name":"bp2066a7","access":"private","args":[{"name":"nnnm","type":"uint128"}],"outputs":{"type":{"response":{"ok":"uint128","error":"uint128"}}}},{"name":"bq52ed6c","access":"private","args":[{"name":"nnnm","type":"uint128"},{"name":"nmmm","type":"uint128"},{"name":"nnmm","type":"uint128"}],"outputs":{"type":{"response":{"ok":"uint128","error":"uint128"}}}},{"name":"cb31dadc","access":"private","args":[{"name":"nnnm","type":"uint128"},{"name":"nmmm","type":"uint128"},{"name":"nnmm","type":"uint128"}],"outputs":{"type":{"response":{"ok":"uint128","error":"uint128"}}}},{"name":"cg7f0657","access":"private","args":[{"name":"nnnm","type":"uint128"},{"name":"mmmm","type":"uint128"}],"outputs":{"type":{"response":{"ok":"uint128","error":"uint128"}}}},{"name":"ct87232b","access":"private","args":[{"name":"nnnm","type":"uint128"}],"outputs":{"type":{"response":{"ok":"uint128","error":"uint128"}}}},{"name":"dh73971f","access":"private","args":[{"name":"nnnm","type":"uint128"},{"name":"nnmm","type":"uint128"}],"outputs":{"type":{"response":{"ok":"uint128","error":"uint128"}}}},{"name":"di79bb03","access":"private","args":[{"name":"nnnm","type":"uint128"}],"outputs":{"type":{"response":{"ok":"uint128","error":"uint128"}}}},{"name":"drbc4b7e","access":"private","args":[{"name":"nnnm","type":"uint128"},{"name":"mmmm","type":"uint128"}],"outputs":{"type":{"response":{"ok":"uint128","error":"uint128"}}}},{"name":"ec6d6433","access":"private","args":[{"name":"nnnm","type":"uint128"}],"outputs":{"type":{"response":{"ok":"uint128","error":"uint128"}}}},{"name":"ep3f81da","access":"private","args":[{"name":"nnnm","type":"uint128"}],"outputs":{"type":{"response":{"ok":"uint128","error":"uint128"}}}},{"name":"fcb38a84","access":"private","args":[{"name":"nnnm","type":"uint128"}],"outputs":{"type":{"response":{"ok":"uint128","error":"uint128"}}}},{"name":"fd387a45","access":"private","args":[{"name":"nnnm","type":"uint128"}],"outputs":{"type":{"response":{"ok":"uint128","error":"uint128"}}}},{"name":"fh58581e","access":"private","args":[{"name":"nnnm","type":"uint128"}],"outputs":{"type":{"response":{"ok":"uint128","error":"uint128"}}}},{"name":"ft3f6ff0","access":"private","args":[{"name":"nnnm","type":"uint128"},{"name":"nmmm","type":"uint128"}],"outputs":{"type":{"response":{"ok":"uint128","error":"uint128"}}}},{"name":"gg93c8a4","access":"private","args":[{"name":"nnnm","type":"uint128"},{"name":"nmmm","type":"uint128"},{"name":"nnmm","type":"uint128"}],"outputs":{"type":{"response":{"ok":"uint128","error":"uint128"}}}},{"name":"gl4a5511","access":"private","args":[{"name":"nnnm","type":"uint128"},{"name":"nnmm","type":"uint128"}],"outputs":{"type":{"response":{"ok":"uint128","error":"uint128"}}}},{"name":"grb02785","access":"private","args":[{"name":"nnnm","type":"uint128"},{"name":"nnmm","type":"uint128"}],"outputs":{"type":{"response":{"ok":"uint128","error":"uint128"}}}},{"name":"hcf3b5de","access":"private","args":[{"name":"nnnm","type":"uint128"},{"name":"mmmm","type":"uint128"},{"name":"nmmm","type":"uint128"},{"name":"nnmm","type":"uint128"}],"outputs":{"type":{"response":{"ok":"uint128","error":"uint128"}}}},{"name":"hf609e77","access":"private","args":[{"name":"nnnm","type":"uint128"},{"name":"mmmm","type":"uint128"}],"outputs":{"type":{"response":{"ok":"uint128","error":"uint128"}}}},{"name":"ib171053","access":"private","args":[{"name":"nnnm","type":"uint128"}],"outputs":{"type":{"response":{"ok":"uint128","error":"uint128"}}}},{"name":"id4ce0ae","access":"private","args":[{"name":"nnnm","type":"uint128"}],"outputs":{"type":{"response":{"ok":"uint128","error":"uint128"}}}},{"name":"ig73e79b","access":"private","args":[{"name":"nnnm","type":"uint128"}],"outputs":{"type":{"response":{"ok":"uint128","error":"uint128"}}}},{"name":"iw542512","access":"private","args":[{"name":"nnnm","type":"uint128"},{"name":"nnmm","type":"uint128"}],"outputs":{"type":{"response":{"ok":"uint128","error":"uint128"}}}},{"name":"iwfd3090","access":"private","args":[{"name":"nnnm","type":"uint128"},{"name":"nnmm","type":"uint128"}],"outputs":{"type":{"response":{"ok":"uint128","error":"uint128"}}}},{"name":"jo30a16e","access":"private","args":[{"name":"nnnm","type":"uint128"},{"name":"nnmm","type":"uint128"}],"outputs":{"type":{"response":{"ok":"uint128","error":"uint128"}}}},{"name":"kh1e9cc1","access":"private","args":[{"name":"nnnm","type":"uint128"},{"name":"mmmm","type":"uint128"},{"name":"nmmm","type":"uint128"}],"outputs":{"type":{"response":{"ok":"uint128","error":"uint128"}}}},{"name":"koeb9a9e","access":"private","args":[{"name":"nnnm","type":"uint128"}],"outputs":{"type":{"response":{"ok":"uint128","error":"uint128"}}}},{"name":"kr17247d","access":"private","args":[{"name":"nnnm","type":"uint128"},{"name":"mmmm","type":"uint128"}],"outputs":{"type":{"response":{"ok":"uint128","error":"uint128"}}}},{"name":"kv2d4920","access":"private","args":[{"name":"nnnm","type":"uint128"},{"name":"nnmm","type":"uint128"}],"outputs":{"type":{"response":{"ok":"uint128","error":"uint128"}}}},{"name":"kw7d0be1","access":"private","args":[{"name":"nnnm","type":"uint128"},{"name":"mmmm","type":"uint128"}],"outputs":{"type":{"response":{"ok":"uint128","error":"uint128"}}}},{"name":"lefeefeb","access":"private","args":[{"name":"nnnm","type":"uint128"}],"outputs":{"type":{"response":{"ok":"uint128","error":"uint128"}}}},{"name":"ma765da6","access":"private","args":[{"name":"nnnm","type":"uint128"}],"outputs":{"type":{"response":{"ok":"uint128","error":"uint128"}}}},{"name":"mh89c09d","access":"private","args":[{"name":"nnnm","type":"uint128"}],"outputs":{"type":{"response":{"ok":"uint128","error":"uint128"}}}},{"name":"mkf90e22","access":"private","args":[{"name":"nnnm","type":"uint128"}],"outputs":{"type":{"response":{"ok":"uint128","error":"uint128"}}}},{"name":"mo811876","access":"private","args":[{"name":"nnnm","type":"uint128"},{"name":"nmmm","type":"uint128"}],"outputs":{"type":{"response":{"ok":"uint128","error":"uint128"}}}},{"name":"mq1170cb","access":"private","args":[{"name":"nnnm","type":"uint128"},{"name":"mmmm","type":"uint128"}],"outputs":{"type":{"response":{"ok":"uint128","error":"uint128"}}}},{"name":"nbc0a5b8","access":"private","args":[{"name":"nnnm","type":"uint128"}],"outputs":{"type":{"response":{"ok":"uint128","error":"uint128"}}}},{"name":"nl531c92","access":"private","args":[{"name":"nnnm","type":"uint128"}],"outputs":{"type":{"response":{"ok":"uint128","error":"uint128"}}}},{"name":"nm1e8059","access":"private","args":[{"name":"nnnm","type":"uint128"}],"outputs":{"type":{"response":{"ok":"uint128","error":"uint128"}}}},{"name":"nmd60d74","access":"private","args":[{"name":"nnnm","type":"uint128"}],"outputs":{"type":{"response":{"ok":"uint128","error":"uint128"}}}},{"name":"nu5f6717","access":"private","args":[{"name":"nnnm","type":"uint128"},{"name":"nnmm","type":"uint128"}],"outputs":{"type":{"response":{"ok":"uint128","error":"uint128"}}}},{"name":"oa77dc0a","access":"private","args":[{"name":"nnnm","type":"uint128"}],"outputs":{"type":{"response":{"ok":"uint128","error":"uint128"}}}},{"name":"oea1b09a","access":"private","args":[{"name":"nnnm","type":"uint128"}],"outputs":{"type":{"response":{"ok":"uint128","error":"uint128"}}}},{"name":"ohadef23","access":"private","args":[{"name":"nnnm","type":"uint128"}],"outputs":{"type":{"response":{"ok":"uint128","error":"uint128"}}}},{"name":"ok43d7b5","access":"private","args":[{"name":"nnnm","type":"uint128"}],"outputs":{"type":{"response":{"ok":"uint128","error":"uint128"}}}},{"name":"opfe2dd9","access":"private","args":[{"name":"nnnm","type":"uint128"},{"name":"nmmm","type":"uint128"}],"outputs":{"type":{"response":{"ok":"uint128","error":"uint128"}}}},{"name":"paa82a6c","access":"private","args":[{"name":"nnnm","type":"uint128"},{"name":"mmmm","type":"uint128"}],"outputs":{"type":{"response":{"ok":"uint128","error":"uint128"}}}},{"name":"pd97781c","access":"private","args":[{"name":"nnnm","type":"uint128"}],"outputs":{"type":{"response":{"ok":"uint128","error":"uint128"}}}},{"name":"ped99370","access":"private","args":[{"name":"nnnm","type":"uint128"}],"outputs":{"type":{"response":{"ok":"uint128","error":"uint128"}}}},{"name":"ppeae64b","access":"private","args":[{"name":"nnnm","type":"uint128"},{"name":"nnmm","type":"uint128"}],"outputs":{"type":{"response":{"ok":"uint128","error":"uint128"}}}},{"name":"py090d89","access":"private","args":[{"name":"nnnm","type":"uint128"}],"outputs":{"type":{"response":{"ok":"uint128","error":"uint128"}}}},{"name":"py3748ff","access":"private","args":[{"name":"nnnm","type":"uint128"},{"name":"mmmm","type":"uint128"},{"name":"nmmm","type":"uint128"},{"name":"nnmm","type":"uint128"}],"outputs":{"type":{"response":{"ok":"uint128","error":"uint128"}}}},{"name":"qc053d70","access":"private","args":[{"name":"nnnm","type":"uint128"},{"name":"mmmm","type":"uint128"}],"outputs":{"type":{"response":{"ok":"uint128","error":"uint128"}}}},{"name":"qke7b42f","access":"private","args":[{"name":"nnnm","type":"uint128"}],"outputs":{"type":{"response":{"ok":"uint128","error":"uint128"}}}},{"name":"qs818638","access":"private","args":[{"name":"nnnm","type":"uint128"},{"name":"mmmm","type":"uint128"}],"outputs":{"type":{"response":{"ok":"uint128","error":"uint128"}}}},{"name":"qtbe1afb","access":"private","args":[{"name":"nnnm","type":"uint128"},{"name":"mmmm","type":"uint128"}],"outputs":{"type":{"response":{"ok":"uint128","error":"uint128"}}}},{"name":"qu5b5859","access":"private","args":[{"name":"nnnm","type":"uint128"}],"outputs":{"type":{"response":{"ok":"uint128","error":"uint128"}}}},{"name":"qwae0380","access":"private","args":[{"name":"nnnm","type":"uint128"}],"outputs":{"type":{"response":{"ok":"uint128","error":"uint128"}}}},{"name":"rjd60cae","access":"private","args":[{"name":"nnnm","type":"uint128"},{"name":"nnmm","type":"uint128"}],"outputs":{"type":{"response":{"ok":"uint128","error":"uint128"}}}},{"name":"sh805a66","access":"private","args":[{"name":"nnnm","type":"uint128"}],"outputs":{"type":{"response":{"ok":"uint128","error":"uint128"}}}},{"name":"sidecb2d","access":"private","args":[{"name":"nnnm","type":"uint128"},{"name":"nnmm","type":"uint128"}],"outputs":{"type":{"response":{"ok":"uint128","error":"uint128"}}}},{"name":"ssbab195","access":"private","args":[{"name":"nnnm","type":"uint128"},{"name":"nnmm","type":"uint128"}],"outputs":{"type":{"response":{"ok":"uint128","error":"uint128"}}}},{"name":"st2b94b2","access":"private","args":[{"name":"nnnm","type":"uint128"},{"name":"nmmm","type":"uint128"}],"outputs":{"type":{"response":{"ok":"uint128","error":"uint128"}}}},{"name":"sw8f2d8f","access":"private","args":[{"name":"nnnm","type":"uint128"}],"outputs":{"type":{"response":{"ok":"uint128","error":"uint128"}}}},{"name":"ta5d490f","access":"private","args":[{"name":"nnnm","type":"uint128"}],"outputs":{"type":{"response":{"ok":"uint128","error":"uint128"}}}},{"name":"td98f6bb","access":"private","args":[{"name":"nnnm","type":"uint128"}],"outputs":{"type":{"response":{"ok":"uint128","error":"uint128"}}}},{"name":"ti2a4b2c","access":"private","args":[{"name":"nnnm","type":"uint128"},{"name":"mmmm","type":"uint128"}],"outputs":{"type":{"response":{"ok":"uint128","error":"uint128"}}}},{"name":"tic69294","access":"private","args":[{"name":"nnnm","type":"uint128"}],"outputs":{"type":{"response":{"ok":"uint128","error":"uint128"}}}},{"name":"ud94f163","access":"private","args":[{"name":"nnnm","type":"uint128"}],"outputs":{"type":{"response":{"ok":"uint128","error":"uint128"}}}},{"name":"uf5cb7a4","access":"private","args":[{"name":"nnnm","type":"uint128"},{"name":"nnmm","type":"uint128"}],"outputs":{"type":{"response":{"ok":"uint128","error":"uint128"}}}},{"name":"uj798252","access":"private","args":[{"name":"nnnm","type":"uint128"},{"name":"mmmm","type":"uint128"}],"outputs":{"type":{"response":{"ok":"uint128","error":"uint128"}}}},{"name":"uqaee6f7","access":"private","args":[{"name":"nnnm","type":"uint128"},{"name":"mmmm","type":"uint128"},{"name":"nmmm","type":"uint128"}],"outputs":{"type":{"response":{"ok":"uint128","error":"uint128"}}}},{"name":"ux1aeb66","access":"private","args":[{"name":"nnnm","type":"uint128"},{"name":"mmmm","type":"uint128"},{"name":"nnmm","type":"uint128"}],"outputs":{"type":{"response":{"ok":"uint128","error":"uint128"}}}},{"name":"uz6432a1","access":"private","args":[{"name":"nnnm","type":"uint128"}],"outputs":{"type":{"response":{"ok":"uint128","error":"uint128"}}}},{"name":"vaabe43a","access":"private","args":[{"name":"nnnm","type":"uint128"}],"outputs":{"type":{"response":{"ok":"uint128","error":"uint128"}}}},{"name":"vj5ae168","access":"private","args":[{"name":"nnnm","type":"uint128"},{"name":"nnmm","type":"uint128"}],"outputs":{"type":{"response":{"ok":"uint128","error":"uint128"}}}},{"name":"vq3d565c","access":"private","args":[{"name":"nnnm","type":"uint128"},{"name":"nmmm","type":"uint128"}],"outputs":{"type":{"response":{"ok":"uint128","error":"uint128"}}}},{"name":"vq8947df","access":"private","args":[{"name":"nnnm","type":"uint128"}],"outputs":{"type":{"response":{"ok":"uint128","error":"uint128"}}}},{"name":"vsbdeffb","access":"private","args":[{"name":"nnnm","type":"uint128"},{"name":"mmmm","type":"uint128"},{"name":"nmmm","type":"uint128"},{"name":"nnmm","type":"uint128"}],"outputs":{"type":{"response":{"ok":"uint128","error":"uint128"}}}},{"name":"vze58301","access":"private","args":[{"name":"nnnm","type":"uint128"}],"outputs":{"type":{"response":{"ok":"uint128","error":"uint128"}}}},{"name":"wf691f44","access":"private","args":[{"name":"nnnm","type":"uint128"}],"outputs":{"type":{"response":{"ok":"uint128","error":"uint128"}}}},{"name":"xbbec8b4","access":"private","args":[{"name":"nnnm","type":"uint128"}],"outputs":{"type":{"response":{"ok":"uint128","error":"uint128"}}}},{"name":"xm07642b","access":"private","args":[{"name":"nnnm","type":"uint128"},{"name":"nnmm","type":"uint128"}],"outputs":{"type":{"response":{"ok":"uint128","error":"uint128"}}}},{"name":"xmfb045c","access":"private","args":[{"name":"nnnm","type":"uint128"}],"outputs":{"type":{"response":{"ok":"uint128","error":"uint128"}}}},{"name":"xs450aa5","access":"private","args":[{"name":"nnnm","type":"uint128"},{"name":"nnmm","type":"uint128"}],"outputs":{"type":{"response":{"ok":"uint128","error":"uint128"}}}},{"name":"ye6b7194","access":"private","args":[{"name":"nnnm","type":"uint128"},{"name":"nmmm","type":"uint128"}],"outputs":{"type":{"response":{"ok":"uint128","error":"uint128"}}}},{"name":"yed1f2a1","access":"private","args":[{"name":"nnnm","type":"uint128"},{"name":"mmmm","type":"uint128"}],"outputs":{"type":{"response":{"ok":"uint128","error":"uint128"}}}},{"name":"yh8f1570","access":"private","args":[{"name":"nnnm","type":"uint128"}],"outputs":{"type":{"response":{"ok":"uint128","error":"uint128"}}}},{"name":"yj237bc7","access":"private","args":[{"name":"nnnm","type":"uint128"},{"name":"mmmm","type":"uint128"}],"outputs":{"type":{"response":{"ok":"uint128","error":"uint128"}}}},{"name":"yte07532","access":"private","args":[{"name":"nnnm","type":"uint128"}],"outputs":{"type":{"response":{"ok":"uint128","error":"uint128"}}}},{"name":"za34ffc4","access":"private","args":[{"name":"nnnm","type":"uint128"},{"name":"mmmm","type":"uint128"}],"outputs":{"type":{"response":{"ok":"uint128","error":"uint128"}}}},{"name":"zgce71b6","access":"private","args":[{"name":"nnnm","type":"uint128"},{"name":"mmmm","type":"uint128"}],"outputs":{"type":{"response":{"ok":"uint128","error":"uint128"}}}},{"name":"zie33a84","access":"private","args":[{"name":"nnnm","type":"uint128"}],"outputs":{"type":{"response":{"ok":"uint128","error":"uint128"}}}},{"name":"zlc6023c","access":"private","args":[{"name":"nnnm","type":"uint128"}],"outputs":{"type":{"response":{"ok":"uint128","error":"uint128"}}}},{"name":"zs3b7eee","access":"private","args":[{"name":"nnnm","type":"uint128"}],"outputs":{"type":{"response":{"ok":"uint128","error":"uint128"}}}},{"name":"zw7342bf","access":"private","args":[{"name":"nnnm","type":"uint128"}],"outputs":{"type":{"response":{"ok":"uint128","error":"uint128"}}}},{"name":"dispatch","access":"public","args":[{"name":"i","type":{"buffer":{"length":3}}},{"name":"nnnm","type":"uint128"},{"name":"nnnn","type":"uint128"},{"name":"mmmm","type":"uint128"},{"name":"nmmm","type":"uint128"},{"name":"nnmm","type":"uint128"}],"outputs":{"type":{"response":{"ok":"uint128","error":"uint128"}}}}],"variables":[],"maps":[],"fungible_tokens":[],"non_fungible_tokens":[]},"sip9":false,"sip10":false,"commission":false,"operable":false}