{"address":"SP2ZNGJ85ENDY6QRHQ5P2D4FXKGZWCKTB2T0Z55KS","name":"creatures-kit","block_height":158114,"burn_block_time_iso":"2024-07-17T08:17:30.000Z","contractInterface":{"functions":[{"name":"callback","access":"public","args":[{"name":"sender","type":"principal"},{"name":"memo","type":{"buffer":{"length":34}}}],"outputs":{"type":{"response":{"ok":"bool","error":"none"}}}},{"name":"dismiss","access":"public","args":[{"name":"amount","type":"uint128"},{"name":"sip10-contract","type":"trait_reference"}],"outputs":{"type":{"response":{"ok":{"tuple":[{"name":"creature-id","type":"uint128"},{"name":"owner","type":"principal"},{"name":"stored-energy","type":"uint128"},{"name":"type","type":{"string-ascii":{"length":12}}}]},"error":"uint128"}}}},{"name":"recruit","access":"public","args":[{"name":"amount","type":"uint128"},{"name":"sip10-contract","type":"trait_reference"}],"outputs":{"type":{"response":{"ok":{"tuple":[{"name":"creature-id","type":"uint128"},{"name":"owner","type":"principal"},{"name":"stored-energy","type":"uint128"},{"name":"type","type":{"string-ascii":{"length":12}}}]},"error":"uint128"}}}},{"name":"store","access":"public","args":[{"name":"sip10-contract","type":"trait_reference"}],"outputs":{"type":{"response":{"ok":{"tuple":[{"name":"creature-id","type":"uint128"},{"name":"owner","type":"principal"},{"name":"stored-energy","type":"uint128"},{"name":"type","type":{"string-ascii":{"length":12}}}]},"error":"uint128"}}}},{"name":"tap","access":"public","args":[{"name":"creature-id","type":"uint128"}],"outputs":{"type":{"response":{"ok":{"tuple":[{"name":"ENERGY","type":"uint128"},{"name":"creature-amount","type":"uint128"},{"name":"creature-id","type":"uint128"},{"name":"type","type":{"string-ascii":{"length":10}}}]},"error":"none"}}}},{"name":"blocks-to-target-energy","access":"read_only","args":[{"name":"creature-id","type":"uint128"},{"name":"user","type":"principal"},{"name":"target-energy","type":"uint128"}],"outputs":{"type":"uint128"}},{"name":"get-blocks-since-last-update","access":"read_only","args":[{"name":"creature-id","type":"uint128"},{"name":"user","type":"principal"}],"outputs":{"type":"uint128"}},{"name":"get-energy-per-block","access":"read_only","args":[{"name":"creature-id","type":"uint128"},{"name":"user","type":"principal"}],"outputs":{"type":"uint128"}},{"name":"get-new-energy","access":"read_only","args":[{"name":"creature-id","type":"uint128"},{"name":"user","type":"principal"}],"outputs":{"type":"uint128"}},{"name":"get-stored-energy","access":"read_only","args":[{"name":"creature-id","type":"uint128"},{"name":"user","type":"principal"}],"outputs":{"type":"uint128"}},{"name":"get-total-tapped-energy","access":"read_only","args":[{"name":"creature-id","type":"uint128"},{"name":"user","type":"principal"}],"outputs":{"type":"uint128"}},{"name":"get-untapped-amount","access":"read_only","args":[{"name":"creature-id","type":"uint128"},{"name":"user","type":"principal"}],"outputs":{"type":{"response":{"ok":"uint128","error":"none"}}}},{"name":"get-user-last-update","access":"read_only","args":[{"name":"creature-id","type":"uint128"},{"name":"user","type":"principal"}],"outputs":{"type":"uint128"}}],"variables":[{"name":"err-nothing-to-tap","type":{"response":{"ok":"none","error":"uint128"}},"access":"constant"},{"name":"err-unauthorized","type":{"response":{"ok":"none","error":"uint128"}},"access":"constant"}],"maps":[{"name":"last-update","key":{"tuple":[{"name":"creature-id","type":"uint128"},{"name":"owner","type":"principal"}]},"value":"uint128"},{"name":"stored-energy","key":{"tuple":[{"name":"creature-id","type":"uint128"},{"name":"owner","type":"principal"}]},"value":"uint128"},{"name":"total-tapped-energy","key":{"tuple":[{"name":"creature-id","type":"uint128"},{"name":"owner","type":"principal"}]},"value":"uint128"}],"fungible_tokens":[],"non_fungible_tokens":[]},"sip9":false,"sip10":false,"commission":false,"operable":false}