{"address":"SP2ZNGJ85ENDY6QRHQ5P2D4FXKGZWCKTB2T0Z55KS","name":"charisma-randomizer-rc1","block_height":170486,"burn_block_time_iso":"2024-10-19T13:43:20.000Z","contractInterface":{"functions":[{"name":"buff-to-u8","access":"private","args":[{"name":"byte","type":{"buffer":{"length":1}}}],"outputs":{"type":"uint128"}},{"name":"lower-16-le","access":"private","args":[{"name":"vrf-seed","type":{"buffer":{"length":32}}}],"outputs":{"type":"uint128"}},{"name":"lower-16-le-inner","access":"private","args":[{"name":"byte","type":{"buffer":{"length":1}}},{"name":"pos","type":"uint128"}],"outputs":{"type":"uint128"}},{"name":"get-random-seed","access":"read_only","args":[],"outputs":{"type":{"response":{"ok":"uint128","error":"none"}}}},{"name":"roll-die","access":"read_only","args":[{"name":"sides","type":"uint128"}],"outputs":{"type":{"response":{"ok":"uint128","error":"none"}}}}],"variables":[],"maps":[],"fungible_tokens":[],"non_fungible_tokens":[]},"sip9":false,"sip10":false,"commission":false,"operable":false}