{"address":"SP4SZE494VC2YC5JYG7AYFQ44F5Q4PYV7DVMDPBG","name":"delegates-handler-v1","block_height":147410,"burn_block_time_iso":"2024-04-23T11:35:43.000Z","contractInterface":{"functions":[{"name":"request-stx-to-stack","access":"private","args":[{"name":"delegate","type":"trait_reference"},{"name":"reserve","type":"trait_reference"},{"name":"amount","type":"uint128"}],"outputs":{"type":{"response":{"ok":"bool","error":"uint128"}}}},{"name":"return-stx-from-stacking","access":"private","args":[{"name":"delegate","type":"trait_reference"},{"name":"reserve","type":"trait_reference"},{"name":"amount","type":"uint128"}],"outputs":{"type":{"response":{"ok":"bool","error":"uint128"}}}},{"name":"handle-excess","access":"public","args":[{"name":"delegate","type":"trait_reference"},{"name":"reserve","type":"trait_reference"}],"outputs":{"type":{"response":{"ok":"uint128","error":"uint128"}}}},{"name":"handle-rewards","access":"public","args":[{"name":"delegate","type":"trait_reference"},{"name":"reserve","type":"trait_reference"},{"name":"rewards-contract","type":"trait_reference"}],"outputs":{"type":{"response":{"ok":"uint128","error":"uint128"}}}},{"name":"revoke","access":"public","args":[{"name":"delegate","type":"trait_reference"},{"name":"reserve","type":"trait_reference"},{"name":"rewards-contract","type":"trait_reference"}],"outputs":{"type":{"response":{"ok":"bool","error":"uint128"}}}},{"name":"revoke-and-delegate","access":"public","args":[{"name":"delegate","type":"trait_reference"},{"name":"reserve","type":"trait_reference"},{"name":"rewards-contract","type":"trait_reference"},{"name":"amount-ustx","type":"uint128"},{"name":"delegate-to","type":"principal"},{"name":"until-burn-ht","type":"uint128"}],"outputs":{"type":{"response":{"ok":"bool","error":"uint128"}}}},{"name":"update-amounts","access":"public","args":[{"name":"delegate","type":"principal"},{"name":"target-locked","type":"uint128"},{"name":"last-locked","type":"uint128"},{"name":"last-unlocked","type":"uint128"}],"outputs":{"type":{"response":{"ok":"bool","error":"uint128"}}}},{"name":"calculate-excess","access":"read_only","args":[{"name":"delegate","type":"principal"}],"outputs":{"type":"uint128"}},{"name":"calculate-rewards","access":"read_only","args":[{"name":"delegate","type":"principal"}],"outputs":{"type":"uint128"}},{"name":"get-last-locked-amount","access":"read_only","args":[{"name":"delegate","type":"principal"}],"outputs":{"type":"uint128"}},{"name":"get-last-selected-pool","access":"read_only","args":[{"name":"delegate","type":"principal"}],"outputs":{"type":"principal"}},{"name":"get-last-unlocked-amount","access":"read_only","args":[{"name":"delegate","type":"principal"}],"outputs":{"type":"uint128"}},{"name":"get-stx-account","access":"read_only","args":[{"name":"account","type":"principal"}],"outputs":{"type":{"tuple":[{"name":"locked","type":"uint128"},{"name":"unlock-height","type":"uint128"},{"name":"unlocked","type":"uint128"}]}}},{"name":"get-target-locked-amount","access":"read_only","args":[{"name":"delegate","type":"principal"}],"outputs":{"type":"uint128"}}],"variables":[{"name":"ERR_DELEGATE_AMOUNT_LOCKED","type":"uint128","access":"constant"}],"maps":[{"name":"last-locked-amount","key":"principal","value":"uint128"},{"name":"last-selected-pool","key":"principal","value":"principal"},{"name":"last-unlocked-amount","key":"principal","value":"uint128"},{"name":"target-locked-amount","key":"principal","value":"uint128"}],"fungible_tokens":[],"non_fungible_tokens":[]},"sip9":false,"sip10":false,"commission":false,"operable":false}