{"address":"SP4SZE494VC2YC5JYG7AYFQ44F5Q4PYV7DVMDPBG","name":"rewards-multi-v1","block_height":155148,"burn_block_time_iso":"2024-06-24T13:56:18.000Z","contractInterface":{"functions":[{"name":"add-rewards-helper","access":"private","args":[{"name":"reward","type":{"tuple":[{"name":"amount","type":"uint128"},{"name":"pool","type":"principal"}]}}],"outputs":{"type":{"response":{"ok":"bool","error":"uint128"}}}},{"name":"add-rewards","access":"public","args":[{"name":"commission","type":"trait_reference"},{"name":"staking","type":"trait_reference"},{"name":"reserve","type":"trait_reference"},{"name":"rewards-list","type":{"list":{"type":{"tuple":[{"name":"amount","type":"uint128"},{"name":"pool","type":"principal"}]},"length":20}}}],"outputs":{"type":{"response":{"ok":"bool","error":"uint128"}}}},{"name":"is-error","access":"read_only","args":[{"name":"response","type":{"response":{"ok":"bool","error":"uint128"}}}],"outputs":{"type":"bool"}}],"variables":[],"maps":[],"fungible_tokens":[],"non_fungible_tokens":[]},"sip9":false,"sip10":false,"commission":false,"operable":false}