{"address":"SPFJEA7AQRT7V1KNGNDB12E3XQS75NJHXN14CZMB","name":"basic","block_height":151685,"burn_block_time_iso":"2024-05-27T06:07:46.000Z","contractInterface":{"functions":[{"name":"say-hi","access":"public","args":[],"outputs":{"type":{"response":{"ok":{"string-ascii":{"length":11}},"error":"none"}}}},{"name":"echo-number","access":"read_only","args":[{"name":"val","type":"int128"}],"outputs":{"type":{"response":{"ok":"int128","error":"none"}}}}],"variables":[],"maps":[],"fungible_tokens":[],"non_fungible_tokens":[]},"sip9":false,"sip10":false,"commission":false,"operable":false}