{"address":"SPTXS2MC77PYCXPFBRJ8PV7RH34PW6QJH46B78F5","name":"treasury-vault","block_height":156327,"burn_block_time_iso":"2024-07-04T02:55:59.000Z","contractInterface":{"functions":[{"name":"admin-only","access":"private","args":[],"outputs":{"type":{"response":{"ok":"bool","error":{"string-ascii":{"length":33}}}}}},{"name":"add-whitelist","access":"public","args":[{"name":"user","type":"principal"}],"outputs":{"type":{"response":{"ok":"bool","error":{"string-ascii":{"length":33}}}}}},{"name":"deposit-for-user","access":"public","args":[{"name":"user","type":"principal"},{"name":"amount","type":"uint128"}],"outputs":{"type":{"response":{"ok":"bool","error":{"string-ascii":{"length":33}}}}}},{"name":"increment-global-total-shares-issued","access":"public","args":[{"name":"amount","type":"uint128"}],"outputs":{"type":{"response":{"ok":"bool","error":{"string-ascii":{"length":33}}}}}},{"name":"increment-global-total-treasury-nav","access":"public","args":[{"name":"amount","type":"uint128"}],"outputs":{"type":{"response":{"ok":"bool","error":{"string-ascii":{"length":33}}}}}},{"name":"mint","access":"public","args":[{"name":"amount","type":"uint128"},{"name":"recipient","type":"principal"}],"outputs":{"type":{"response":{"ok":"bool","error":"uint128"}}}},{"name":"process-withdrawal","access":"public","args":[],"outputs":{"type":{"response":{"ok":"bool","error":{"string-ascii":{"length":33}}}}}},{"name":"remove-whitelist","access":"public","args":[{"name":"user","type":"principal"}],"outputs":{"type":{"response":{"ok":"bool","error":{"string-ascii":{"length":33}}}}}},{"name":"request-withdrawal","access":"public","args":[{"name":"share-amount","type":"uint128"}],"outputs":{"type":{"response":{"ok":"bool","error":{"string-ascii":{"length":38}}}}}},{"name":"set-global-total-shares-issued","access":"public","args":[{"name":"amount","type":"uint128"}],"outputs":{"type":{"response":{"ok":"bool","error":{"string-ascii":{"length":33}}}}}},{"name":"set-global-total-treasury-nav","access":"public","args":[{"name":"new-value","type":"uint128"}],"outputs":{"type":{"response":{"ok":"bool","error":{"string-ascii":{"length":33}}}}}},{"name":"transfer","access":"public","args":[{"name":"amount","type":"uint128"},{"name":"sender","type":"principal"},{"name":"recipient","type":"principal"},{"name":"memo","type":{"optional":{"buffer":{"length":34}}}}],"outputs":{"type":{"response":{"ok":"bool","error":"uint128"}}}},{"name":"calculate-shares","access":"read_only","args":[{"name":"amount","type":"uint128"}],"outputs":{"type":"uint128"}},{"name":"calculate-tokens","access":"read_only","args":[{"name":"share-amount","type":"uint128"}],"outputs":{"type":"uint128"}},{"name":"get-balance","access":"read_only","args":[{"name":"who","type":"principal"}],"outputs":{"type":{"response":{"ok":"uint128","error":"none"}}}},{"name":"get-decimals","access":"read_only","args":[],"outputs":{"type":{"response":{"ok":"uint128","error":"none"}}}},{"name":"get-global-total-shares-issued","access":"read_only","args":[],"outputs":{"type":{"response":{"ok":"uint128","error":"none"}}}},{"name":"get-global-total-treasury-nav","access":"read_only","args":[],"outputs":{"type":{"response":{"ok":"uint128","error":"none"}}}},{"name":"get-name","access":"read_only","args":[],"outputs":{"type":{"response":{"ok":{"string-ascii":{"length":4}},"error":"none"}}}},{"name":"get-symbol","access":"read_only","args":[],"outputs":{"type":{"response":{"ok":{"string-ascii":{"length":4}},"error":"none"}}}},{"name":"get-token-uri","access":"read_only","args":[],"outputs":{"type":{"response":{"ok":{"optional":"none"},"error":"none"}}}},{"name":"get-total-supply","access":"read_only","args":[],"outputs":{"type":{"response":{"ok":"uint128","error":"none"}}}},{"name":"get-withdrawal","access":"read_only","args":[{"name":"id","type":"uint128"}],"outputs":{"type":{"response":{"ok":{"tuple":[{"name":"share-amount","type":"uint128"},{"name":"token-amount","type":"uint128"},{"name":"user","type":"principal"},{"name":"withdrawal-completed","type":"bool"}]},"error":{"string-ascii":{"length":32}}}}}},{"name":"is-whitelisted","access":"read_only","args":[{"name":"user","type":"principal"}],"outputs":{"type":{"response":{"ok":"bool","error":"none"}}}}],"variables":[{"name":"contract-owner","type":"principal","access":"constant"},{"name":"err-not-token-owner","type":{"response":{"ok":"none","error":"uint128"}},"access":"constant"},{"name":"err-owner-only","type":{"response":{"ok":"none","error":"uint128"}},"access":"constant"},{"name":"current-withdrawal-request","type":"uint128","access":"variable"},{"name":"global-total-shares-issued","type":"uint128","access":"variable"},{"name":"global-total-treasury-nav","type":"uint128","access":"variable"},{"name":"total-withdrawal-requests","type":"uint128","access":"variable"}],"maps":[{"name":"whitelist","key":"principal","value":"bool"},{"name":"withdrawal-queue","key":"uint128","value":{"tuple":[{"name":"share-amount","type":"uint128"},{"name":"token-amount","type":"uint128"},{"name":"user","type":"principal"},{"name":"withdrawal-completed","type":"bool"}]}}],"fungible_tokens":[{"name":"ustb-token"}],"non_fungible_tokens":[]},"sip9":false,"sip10":true,"commission":false,"operable":false}